banrieen_PyUnitReport-0.1.4.dist-info/DESCRIPTION.rst
banrieen_PyUnitReport-0.1.4.dist-info/METADATA
banrieen_PyUnitReport-0.1.4.dist-info/RECORD
banrieen_PyUnitReport-0.1.4.dist-info/WHEEL
banrieen_PyUnitReport-0.1.4.dist-info/metadata.json
banrieen_PyUnitReport-0.1.4.dist-info/top_level.txt
examples/__init__.py
examples/example_testcase.py
pyunitreport/HtmlTestResult.py
pyunitreport/HtmlTestRunner.py
pyunitreport/__init__.py
pyunitreport/template/report_template.html
