Metadata-Version: 2.0
Name: banrieen-PyUnitReport
Version: 0.1.4
Summary: A unit test runner for Python, and generate HTML reports.
Home-page: https://github.com/banrieen/PyUnitReport.git
Author: Ordanis Sanchez Suero, Leo Lee, banrieen
Author-email: ban.rieen@gmail.com
License: MIT license
Keywords: HtmlTestRunner TestRunner pyUnit Html Reports
Platform: UNKNOWN
Classifier: Development Status :: 3 - Alpha
Classifier: Intended Audience :: Developers
Classifier: License :: OSI Approved :: MIT License
Classifier: Natural Language :: English
Classifier: Programming Language :: Python :: 2.7
Classifier: Programming Language :: Python :: 3.3
Classifier: Programming Language :: Python :: 3.4
Classifier: Programming Language :: Python :: 3.5
Classifier: Programming Language :: Python :: 3.6
Requires-Dist: jinja2
